src/__init__.py
src/exception.py
src/logger.py
src/utils.py
src/components/__init__.py
src/components/data_ingestion.py
src/components/data_transformation.py
src/components/model_trainer.py
DMWT-0.0.1.dist-info/METADATA
DMWT-0.0.1.dist-info/WHEEL
DMWT-0.0.1.dist-info/top_level.txt
DMWT-0.0.1.dist-info/RECORD
