Metadata-Version: 2.1
Name: DMWT
Version: 0.0.1
Author: Vikrant
Author-email: vikrantmohite9029@gmail.com
Requires-Dist: category-encoders (==2.6.0)
Requires-Dist: Flask (==2.2.2)
Requires-Dist: jsonschema (==4.16.0)
Requires-Dist: numpy (==1.23.3)
Requires-Dist: pandas (==1.5.0)
Requires-Dist: requests (==2.28.1)
Requires-Dist: scikit-image (==0.19.3)
Requires-Dist: scikit-learn (==1.1.2)
Requires-Dist: sklearn (==0.0)
Requires-Dist: xgboost (==1.5.0)
Requires-Dist: matplotlib
Requires-Dist: seaborn
Requires-Dist: dill
Requires-Dist: imbalanced-learn
